MANIFEST.in
README.md
keplergl-jupyter.json
setup.cfg
setup.py
bergkvist_keplergl.egg-info/PKG-INFO
bergkvist_keplergl.egg-info/SOURCES.txt
bergkvist_keplergl.egg-info/dependency_links.txt
bergkvist_keplergl.egg-info/not-zip-safe
bergkvist_keplergl.egg-info/requires.txt
bergkvist_keplergl.egg-info/top_level.txt
keplergl/__init__.py
keplergl/_version.py
keplergl/keplergl.py
keplergl/static/extension.js
keplergl/static/extension.js.map
keplergl/static/index.js
keplergl/static/index.js.map
keplergl/static/keplergl.html
keplergl/static/main.js