Metadata-Version: 2.1
Name: bergkvist-keplergl
Version: 0.3.0
Summary: This is a simple jupyter widget for kepler.gl, an advanced geospatial visualization tool, to render large-scale interactive maps.
Home-page: https://github.com/keplergl/kepler.gl/tree/master/bindings/kepler.gl-jupyter
Author: Shan He
Author-email: shan@uber.com
License: UNKNOWN
Keywords: ipython,jupyter,widgets,geospatial,visualization,webGL
Platform: UNKNOWN
Classifier: Development Status :: 4 - Beta
Classifier: Framework :: IPython
Classifier: Intended Audience :: Developers
Classifier: Intended Audience :: Science/Research
Classifier: Topic :: Multimedia :: Graphics
Classifier: Programming Language :: Python :: 2
Classifier: Programming Language :: Python :: 2.7
Classifier: Programming Language :: Python :: 3
Classifier: Programming Language :: Python :: 3.3
Classifier: Programming Language :: Python :: 3.4
Classifier: Programming Language :: Python :: 3.5
